desktop_icon_maker/__init__.py
desktop_icon_maker/main.py
desktop_icon_maker/utils.py
desktop_icon_maker-0.1.0.dist-info/LICENSE
desktop_icon_maker-0.1.0.dist-info/METADATA
desktop_icon_maker-0.1.0.dist-info/WHEEL
desktop_icon_maker-0.1.0.dist-info/entry_points.txt
desktop_icon_maker-0.1.0.dist-info/top_level.txt
desktop_icon_maker-0.1.0.dist-info/RECORD
