Metadata-Version: 2.1
Name: desktop-icon-maker
Version: 0.1.0
Summary: Create .desktop shortcuts for any URL
Home-page: https://github.com/himanshu-kr-jha
Author: Himanshu Kumar Jha
Author-email: himanshukrjha004@gmail.com
Classifier: Programming Language :: Python :: 3
Classifier: License :: OSI Approved :: MIT License
Classifier: Operating System :: OS Independent
Requires-Python: >=3.6
License-File: LICENSE
